LICENSE
MANIFEST.in
README.md
requirements.txt
setup.cfg
setup.py
exec/liblink_crawl
exec/liblink_resource_summary
exec/liblink_title_report
exec/liblinklist
librarylink.egg-info/PKG-INFO
librarylink.egg-info/SOURCES.txt
librarylink.egg-info/dependency_links.txt
librarylink.egg-info/requires.txt
librarylink.egg-info/top_level.txt
pylib/__init__.py
pylib/listmix.py
pylib/resource.py
pylib/scrapy_tools.py
pylib/site.py
pylib/util.py
pylib/version.py
pylib/crawler/__init__.py
pylib/crawler/framework.py
test/resource/csvdedup.py
test/resource/csvexport.py
test/resource/ntriplify.py
test/resource/quickinfo.py