Metadata-Version: 2.1
Name: librarylink
Version: 0.5.1
Summary: ('Tools for working with Library.Link',)
Home-page: http://zepheira.com/
Author: Uche Ogbuji
Author-email: uche@ogbuji.net
Maintainer: Zepheira
Maintainer-email: uche@zepheira.com
License: License :: OSI Approved :: Apache Software License
Keywords: xml,web,data
Platform: UNKNOWN
Classifier: Programming Language :: Python
Classifier: Programming Language :: Python :: 3
Classifier: Development Status :: 3 - Alpha
Classifier: Intended Audience :: Developers
Classifier: License :: OSI Approved :: Apache Software License
Classifier: Operating System :: OS Independent
Classifier: Topic :: Software Development :: Libraries :: Python Modules
Classifier: Topic :: Internet :: WWW/HTTP
